visualize_tools/__init__.py
visualize_tools/image_set_difference.py
visualize_tools/metrics.py
visualize_tools/metrics_lpips.py
visualize_tools/utils.py
visualize_tools-0.0.3.dist-info/licenses/LICENSE
visualize_tools-0.0.3.dist-info/METADATA
visualize_tools-0.0.3.dist-info/WHEEL
visualize_tools-0.0.3.dist-info/entry_points.txt
visualize_tools-0.0.3.dist-info/top_level.txt
visualize_tools-0.0.3.dist-info/RECORD
