Metadata-Version: 2.4
Name: visualize_tools
Version: 0.0.3
Summary: A set of tools for visualization
Author: changhaoxuan23
License-Expression: AGPL-3.0-or-later
Project-URL: Homepage, https://github.com/changhaoxuan23/visualize_tools
Project-URL: Issues, https://github.com/changhaoxuan23/visualize_tools/issues
Classifier: Development Status :: 2 - Pre-Alpha
Classifier: Environment :: Console
Classifier: Environment :: GPU :: NVIDIA CUDA
Classifier: Intended Audience :: Science/Research
Classifier: Operating System :: OS Independent
Classifier: Programming Language :: Python :: 3 :: Only
Classifier: Topic :: Scientific/Engineering :: Visualization
Requires-Python: >=3.11
License-File: LICENSE
Requires-Dist: pillow
Requires-Dist: numpy
Provides-Extra: lpips
Requires-Dist: torch; extra == "lpips"
Requires-Dist: torchvision; extra == "lpips"
Dynamic: license-file
